{
  "about.date": "Builddatum:",
  "about.enterpriseEditionLearn": "Mear ynformaasje oer de Bedriuws-edysje op ",
  "about.enterpriseEditionSt": "Moderne kommunikaasje efter jo eigen firewall.",
  "about.enterpriseEditione1": "Bedriuwsedysje",
  "about.hash": "Buildhash:",
  "about.hashee": "EE-buildhash:",
  "about.teamEditionLearn": "Wurd lid fan de Mattermost-mienskip op ",
  "about.teamEditionSt": "Alle teamkommunikaasje op ien plak, troch te sykjen en fan oeral berikber.",
  "about.teamEditiont0": "Team-edysje",
  "about.teamEditiont1": "Bedriuws-edysje",
  "about.title": "Ynfo oer {appTitle}",
  "api.channel.add_guest.added": "{addedUsername} waard troch {username} as gast tafoege oan it kanaal.",
  "api.channel.add_member.added": "{addedUsername} is troch {username} oan it kanaal tafoege.",
  "api.channel.guest_join_channel.post_and_forget": "{username} is as gast yn it kanaal kommen.",
  "apps.error": "Flater: {error}",
  "apps.error.command.field_missing": "Ferplichte fjilden ûntbrekke: ‘{fieldName}’.",
  "apps.error.command.same_channel": "Kanaal werhelle foar fjild ‘{fieldName}’: ‘{option}’.",
  "apps.error.command.same_option": "Opsje werhelle foar fjild ‘{fieldName}’: ‘{option}’.",
  "apps.error.command.same_user": "Brûker werhelle foar fjild ‘{fieldName}’: ‘{option}’.",
  "apps.error.command.unknown_channel": "Unbekend kanaal foar fjild ‘{fieldName}’: ‘{option}’.",
  "apps.error.command.unknown_option": "Unbekende opsje foar fjild ‘{fieldName}’: ‘{option}’.",
  "apps.error.command.unknown_user": "Unbekende brûker foar fjild ‘{fieldName}’: ‘{option}’.",
  "apps.error.form.no_form": "‘form’ is net definiearre.",
  "apps.error.form.no_lookup": "‘lookup’ is net definiearre.",
  "apps.error.form.no_source": "‘source’ is net definiearre.",
  "apps.error.form.refresh_no_refresh": "Oprop refresh op gjin-refresh-fjild.",
  "apps.error.form.submit.pretext": "Der is in flater bard by it ferstjoeren fan de modal. Nim kontakt op mei de ûntwikkeler fan de app. Details: {details}",
  "apps.error.lookup.error_preparing_request": "Flater by it tarêden fan it lookuprequest: : {errorMessage}",
  "apps.error.malformed_binding": "Dizze ferbining is net korrekt oanmakke. Nim kontakt op mei de ûntwikkeler fan de app.",
  "apps.error.parser": "Ferwurkingsflater: {error}",
  "apps.error.parser.empty_value": "lege wearden binne net tastien",
  "apps.error.parser.execute_non_leaf": "Jo moatte in subkommando kieze.",
  "apps.error.parser.missing_binding": "Untbrekkende opdrachtbiningen.",
  "apps.error.parser.missing_field_value": "Field value ûntbrekt.",
  "apps.error.parser.missing_list_end": "Listslútingsteken ferwacht.",
  "apps.error.parser.missing_quote": "Passend dûbeld oanhellingsteken foar ein fan ynfier ferwacht.",
  "apps.error.parser.missing_source": "Formulier hat gjin submit en gjin source.",
  "apps.error.parser.missing_submit": "Gjin submit call yn ferbining of form.",
  "apps.error.parser.missing_tick": "Passende tick quote ferwacht foar ein fan input.",
  "apps.error.parser.multiple_equal": "Mearfâldige ‘=’-tekens binne net tastien.",
  "apps.error.parser.no_argument_pos_x": "Kin it argumint net identifisearje.",
  "apps.error.parser.no_bindings": "Gjin command bindings.",
  "apps.error.parser.no_form": "Gjin formulier fûn.",
  "apps.error.parser.no_match": "‘{command}’: Gjin oerienkommende opdracht yn dizze wurkromte fûn.",
  "apps.error.parser.no_slash_start": "Commando moat begjinne mei in ‘/’.",
  "apps.error.parser.unexpected_character": "Unferwacht karakter.",
  "apps.error.parser.unexpected_comma": "Unferwachte komma.",
  "apps.error.parser.unexpected_error": "Unferwachte flater.",
  "apps.error.parser.unexpected_flag": "Opdracht akseptearret flagge ‘{flagName}’ net.",
  "apps.error.parser.unexpected_squared_bracket": "Unferwachte listiepening.",
  "apps.error.parser.unexpected_state": "Unberikber: Unferwachte steat yn matchBinding: ‘{state}’.",
  "apps.error.parser.unexpected_whitespace": "Unberikber: Unferwachte spaasjes.",
  "apps.error.responses.form.no_form": "It antwurdtype is ‘form’, mar der is gjin form yn it antwurd opnommen.",
  "apps.error.responses.navigate.no_url": "Response type is ‘navigate’, mar der is gjin URL yn de response opnommen.",
  "apps.error.responses.unexpected_error": "In ûnferwachte flater ûntfongen.",
  "apps.error.responses.unknown_type": "It app-antwurdtype wurdt net stipe. Type antwurd: {type}.",
  "apps.error.unknown": "Der is in ûnbekende flater bard.",
  "apps.suggestion.dynamic.error": "Dynamyske seleksjeflater",
  "apps.suggestion.errors.parser_error": "Flater by it ferwurkjen",
  "apps.suggestion.no_dynamic": "Gjin gegevens foar dynamyske suggestjes ûntfongen",
  "apps.suggestion.no_static": "Gjin passende opsjes.",
  "apps.suggestion.no_suggestion": "Gjin passende suggestjes.",
  "archivedChannelMessage": "Jo besjogge in **argivearre kanaal**. Der kinne gjin nije berjochten pleatst wurde.",
  "center_panel.archived.closeChannel": "Kanaal slute",
  "channel_header.directchannel.you": "{displayname} (jo) ",
  "channel_header.manageMembers": "Leden beheare",
  "channel_header.viewMembers": "Leden besjen",
  "channel_loader.someone": "Immen",
  "channel_modal.cancel": "Annulearje",
  "channel_notifications.muteChannel.settings": "Kanaal dôvje",
  "combined_system_message.added_to_channel.many_expanded": "{users} en {lastUser} binne **oan it kanaal tafoege** troch {actor}.",
  "combined_system_message.added_to_channel.one": "{firstUser} **oan it kanaal tafoege** troch {actor}.",
  "combined_system_message.added_to_channel.one_you": "Jo binne troch {actor} **oan it kanaal tafoege**.",
  "combined_system_message.added_to_channel.two": "{firstUser} en {secondUser} troch {actor} **oan it kanaal tafoege**.",
  "combined_system_message.added_to_team.many_expanded": "{users} en {lastUser} binne troch {actor} **oan it team tafoege**.",
  "combined_system_message.added_to_team.one": "{firstUser} troch {actor} **oan it team tafoege**.",
  "combined_system_message.added_to_team.one_you": "Jo binne troch {actor} **oan it team tafoege**.",
  "combined_system_message.added_to_team.two": "{firstUser} en {secondUser} binne troch {actor} **oan it team tafoege**.",
  "combined_system_message.joined_channel.many_expanded": "{users} en {lastUser} **binne by it kanaal oansluten**.",
  "combined_system_message.joined_channel.one": "{firstUser} **is by it kanaal oansluten**.",
  "combined_system_message.joined_channel.one_you": "Jo **binne by it kanaal oansluten**.",
  "combined_system_message.joined_channel.two": "{firstUser} en {secondUser} **binne by it kanaal oansluten**.",
  "combined_system_message.joined_team.many_expanded": "{users} en {lastUser} **binne yn it team kommen **.",
  "combined_system_message.joined_team.one": "{firstUser} **is by it team kommen**.",
  "combined_system_message.joined_team.one_you": "Jo **binne by it team oansluten**.",
  "combined_system_message.joined_team.two": "{firstUser} en {secondUser} **binne by it team kommen**.",
  "combined_system_message.left_channel.many_expanded": "{users} en {lastUser} **hawwe it kanaal ferlitten**.",
  "combined_system_message.left_channel.one": "{firstUser} **hawwe it kanaal ferlitten**.",
  "combined_system_message.left_channel.one_you": "Jo **hawwe it kanaal ferlitten**.",
  "combined_system_message.left_channel.two": "{firstUser} en {secondUser} **hawwe it kanaal ferlitten**.",
  "combined_system_message.left_team.many_expanded": "{users} and {lastUser} **hawwe it team ferlitten**.",
  "combined_system_message.left_team.one": "{firstUser} **hat it team ferlitten**.",
  "combined_system_message.left_team.one_you": "Jo **hawwe it team ferlitten**.",
  "combined_system_message.left_team.two": "{firstUser} en {secondUser} **hawwe it team ferlitten**.",
  "combined_system_message.removed_from_channel.many_expanded": "{users} en {lastUser} waarden **út it kanaal fuortsmiten**.",
  "combined_system_message.removed_from_channel.one": "{firstUser} waard **út it kanaal fuortsmiten**.",
  "combined_system_message.removed_from_channel.one_you": "Jo waarden **út it kanaal fuortsmiten**.",
  "combined_system_message.removed_from_channel.two": "{firstUser} en {secondUser} waarden **út it kanaal fuortsmiten**.",
  "combined_system_message.removed_from_team.many_expanded": "{users} en {lastUser} waarden **út it team fuortsmiten**.",
  "combined_system_message.removed_from_team.one": "{firstUser} waard **út it team fuortsmiten**.",
  "combined_system_message.removed_from_team.one_you": "Jo waarden **út it team fuortsmiten**.",
  "combined_system_message.removed_from_team.two": "{firstUser} en {secondUser} waarden **út it team fuortmiten**.",
  "combined_system_message.you": "jo",
  "create_post.write": "Nei {channelDisplayName} skriuwe",
  "custom_status.expiry.until": "Oant",
  "custom_status.expiry_dropdown.dont_clear": "Net wiskje",
  "custom_status.expiry_dropdown.four_hours": "4 oeren",
  "custom_status.expiry_dropdown.one_hour": "1 oere",
  "custom_status.expiry_dropdown.thirty_minutes": "30 minuten",
  "custom_status.expiry_dropdown.this_week": "Dizze wike",
  "custom_status.expiry_dropdown.today": "Hjoed",
  "custom_status.set_status": "In steat ynstelle",
  "custom_status.suggestions.in_a_meeting": "Yn gearkomste",
  "custom_status.suggestions.on_a_vacation": "Op fakânsje",
  "custom_status.suggestions.out_for_lunch": "Lunch",
  "custom_status.suggestions.out_sick": "Siik",
  "custom_status.suggestions.recent_title": "RESINT",
  "custom_status.suggestions.title": "SUGGESTJES",
  "custom_status.suggestions.working_from_home": "Thúswurk",
  "date_separator.today": "Hjoed",
  "date_separator.yesterday": "Juster",
  "edit_post.editPost": "It berjocht bewurkje…",
  "emoji_picker.activities": "Aktiviteiten",
  "emoji_picker.animals-nature": "Bisten & natuer",
  "emoji_picker.custom": "Oanpast",
  "emoji_picker.flags": "Flaggen",
  "emoji_picker.food-drink": "Iten & drinken",
  "emoji_picker.objects": "Foarwerpen",
  "emoji_picker.people-body": "Minsk & lichem",
  "emoji_picker.searchResults": "Sykresultaten",
  "emoji_picker.smileys-emotion": "Smileys & emoticons",
  "emoji_picker.symbols": "Symboalen",
  "integrations.add": "Tafoegje",
  "intro_messages.anyMember": " Elk lid kin dit kanaal lêze en folgje.",
  "intro_messages.beginning": "Begjin fan {name}",
  "intro_messages.creator": "Dit is de start fan it {name}-kanaal, makke troch {creator} op {date}.",
  "intro_messages.creatorPrivate": "Dit is de start fan it {name}-priveekanaal, makke troch {creator} op {date}.",
  "intro_messages.group_message": "Dit is de start fan jo groepsberjochtskiednis mei dizze teamleden. Berjochten en bestannen dy’t dield wurde, wurde hjir net toand oan minsken bûten dit gebied.",
  "intro_messages.noCreator": "Dit is de start fan it {name}-kanaal, makke op {date}.",
  "intro_messages.onlyInvited": " Allinnich útnûge dielnimmers kinne dizze priveegroep besjen.",
  "last_users_message.added_to_channel.type": "is troch {actor} **oan it kanaal tafoege**.",
  "last_users_message.added_to_team.type": "is troch {actor} **oan it team tafoege**.",
  "last_users_message.first": "{firstUser} en ",
  "last_users_message.joined_channel.type": "**is by it kanaal oansluten**.",
  "last_users_message.joined_team.type": "**is by it team oansluten**.",
  "last_users_message.left_channel.type": "**hat it kanaal ferlitten**.",
  "last_users_message.left_team.type": "**hat it team ferlitten**.",
  "last_users_message.others": "{numOthers} oaren ",
  "last_users_message.removed_from_channel.type": "waard **út it kanaal fuortsmiten**.",
  "last_users_message.removed_from_team.type": "waard **út it team fuortsmiten**.",
  "login.email": "E-mailadres",
  "login.invalidPassword": "Jo wachtwurd is net korrekt.",
  "login.ldapUsername": "AD/LDAP-brûkersnamme",
  "login.ldapUsernameLower": "AD/LDAP-brûkersnamme",
  "login.noEmail": "Fier jo e-mailadres yn",
  "login.noEmailLdapUsername": "Fier jo e-mailadres of {ldapUsername} yn",
  "login.noEmailUsername": "Fier jo e-mailadres of brûkersnamme yn",
  "login.noEmailUsernameLdapUsername": "Fier jo e-mailadres, brûkersnamme of {ldapUsername} yn",
  "login.noLdapUsername": "Fier jo {ldapUsername} yn",
  "login.noPassword": "Fier jo wachtwurd yn",
  "login.noUsername": "Fier jo brûkersnamme yn",
  "login.noUsernameLdapUsername": "Fier jo brûkersnamme of {ldapUsername} yn",
  "login.userNotFound": "Wy koene gjin account mei jo oanmeldgegevens fine.",
  "login.username": "Brûkersnamme",
  "login_mfa.token": "MFA-token",
  "modal.manual_status.auto_responder.message_": "Wil je jouw status wijzigen naar \"{status}\" en Automatisch Antwoorden uitschakelen?",
  "modal.manual_status.auto_responder.message_away": "Wil je de status wijzigen naar \"Afwezig\" en Automatisch Antwoorden uitschakelen?",
  "modal.manual_status.auto_responder.message_dnd": "Wil je de status wijzigen naar \"Niet Storen\" en Automatisch Antwoorden uitschakelen?",
  "modal.manual_status.auto_responder.message_offline": "Wil je de status wijzigen naar \"Offline\" en Automatisch Antwoorden uitschakelen?",
  "modal.manual_status.auto_responder.message_online": "Wil je de status wijzigen naar \"Online\" en Automatisch Antwoorden uitschakelen?",
  "more_channels.noMore": "Geen kanalen beschikbaar waar aan deelgenomen kan worden",
  "more_channels.title": "Meer kanalen",
  "msg_typing.areTyping": "{users} en {last} zijn aan het typen...",
  "msg_typing.isTyping": "{user} typt...",
  "password_form.title": "Wachtwoord reset",
  "password_send.checkInbox": "Controleer je inbox.",
  "password_send.description": "Om uw wachtwoord opnieuw in te stellen voert u het e-mailadres in dat u heeft gebruikt om uzelf aan te melden",
  "password_send.error": "Vul een geldig e-mail adres in.",
  "password_send.link": "Als het account bestaat, wordt er een e-mail voor het resetten van wachtwoorden verzonden naar:",
  "password_send.reset": "Reset wachtwoord",
  "permalink.error.access": "Permalink behoort toe aan een verwijderd bericht of aan een kanaal waar je geen toegang tot hebt.",
  "permalink.show_dialog_warn.join": "Lid worden",
  "permalink.show_dialog_warn.title": "Word lid van het privékanaal",
  "post_body.check_for_out_of_channel_mentions.link.and": " en ",
  "post_body.check_for_out_of_channel_mentions.link.private": "voeg ze toe aan dit privé-kanaal",
  "post_body.check_for_out_of_channel_mentions.link.public": "ze toevoegen aan het kanaal",
  "post_body.check_for_out_of_channel_mentions.message_last": "? Ze zullen toegang hebben tot de volledige berichtgeschiedenis.",
  "post_body.deleted": "(bericht verwijderd)",
  "post_info.auto_responder": "AUTOMATISCH ANTWOORD",
  "post_info.bot": "BOT",
  "post_info.del": "Verwijderen",
  "post_info.edit": "Bewerken",
  "post_info.guest": "GAST",
  "post_info.system": "Systeem",
  "posts_view.newMsg": "Nieuwe Berichten",
  "rhs_thread.rootPostDeletedMessage.body": "Een deel van dit draadje is gewist vanwege het gegevensbewaarbeleid. Je kan niet meer reageren op dit draadje.",
  "search_bar.search": "Zoeken",
  "search_header.results": "Zoekresultaten",
  "search_header.title2": "Recente vermeldingen",
  "search_item.channelArchived": "Gearchiveerd",
  "sidebar.unreads": "Meer ongelezen berichten",
  "status_dropdown.set_away": "Afwezig",
  "status_dropdown.set_dnd": "Niet Storen",
  "status_dropdown.set_offline": "Offline",
  "status_dropdown.set_online": "Online",
  "status_dropdown.set_ooo": "Out Of Office",
  "suggestion.mention.all": "Verwittig iedereen in dit kanaal",
  "suggestion.mention.channel": "Verwittig iedereen in dit kanaal",
  "suggestion.mention.channels": "Mijn Kanalen",
  "suggestion.mention.groups": "Groepsvermeldingen",
  "suggestion.mention.here": "Verwittig iedereen in dit kanaal",
  "suggestion.mention.members": "Kanaalleden",
  "suggestion.mention.morechannels": "Andere Kanalen",
  "suggestion.mention.nonmembers": "Niet in kanaal",
  "suggestion.mention.special": "Speciale Vermeldingen",
  "suggestion.search.direct": "Privé bericht",
  "suggestion.search.private": "Privé-kanalen",
  "suggestion.search.public": "Publieke kanalen",
  "terms_of_service.agreeButton": "Ik ga akkoord",
  "terms_of_service.api_error": "De opdracht kan niet worden voltooid. Als dit probleem zich blijft voordoen, neem dan contact op met de Systeembeheerder.",
  "user.settings.display.clockDisplay": "Klok weergave",
  "user.settings.display.militaryClock": "24 uren klok (bijvoorbeeld: 16:00)",
  "user.settings.display.normalClock": "12 uren klok (bijvoorbeeld: 4:00 PM)",
  "user.settings.display.preferTime": "Selecteer hoe u de tijd wilt zien.",
  "user.settings.general.email": "E-mail",
  "user.settings.general.emailGitlabCantUpdate": "Login gebeurt via GitLab. Het e-mail adres kan niet bijgewerkt worden. Het e-mailadres dat gebruikt wordt voor meldingen is {email}.",
  "user.settings.general.emailGoogleCantUpdate": "Login gebeurt via Google. Het e-mail adres kan niet bijgewerkt worden. Het e-mailadres dat gebruikt wordt voor meldingen is {email}.",
  "user.settings.general.emailLdapCantUpdate": "Login gebeurt via AD/LDAP. Het e-mail adres kan niet bijgewerkt worden. Het e-mailadres dat gebruikt wordt voor meldingen is {email}.",
  "user.settings.general.emailOffice365CantUpdate": "Login gebeurt via Office 365. Het e-mailadres kan niet bijgewerkt worden. Het e-mail adres dat gebruikt wordt voor meldingen is {email}.",
  "user.settings.general.emailSamlCantUpdate": "Login gebeurt via SAML. Het e-mail adres kan niet bijgewerkt worden. Het e-mailadres dat gebruikt wordt voor meldingen is {email}.",
  "user.settings.general.field_handled_externally": "Dit veld word gebruikt door jouw login provider. Als je het wilt veranderen, moet je dat via de login provider doen.",
  "user.settings.general.firstName": "Voornaam",
  "user.settings.general.lastName": "Achternaam",
  "user.settings.general.nickname": "Roepnaam",
  "user.settings.general.position": "Positie",
  "user.settings.general.username": "Gebruikersnaam",
  "user.settings.modal.display": "Weergave",
  "user.settings.modal.notifications": "Meldingen",
  "user.settings.notifications.allActivity": "Voor alle activiteiten",
  "user.settings.notifications.comments": "Antwoord meldingen",
  "user.settings.notifications.email.disabled": "E-mailmeldingen zijn niet ingeschakeld",
  "user.settings.notifications.email.everyHour": "Elk uur",
  "user.settings.notifications.email.immediately": "Onmiddellijk",
  "user.settings.notifications.email.never": "Nooit",
  "user.settings.notifications.email.send": "Stuur e-mailmeldingen",
  "user.settings.notifications.emailInfo": "E-mailmeldingen worden verzonden voor vermeldingen en directe berichten wanneer u offline of weg bent voor meer dan 5 minuten.",
  "user.settings.notifications.never": "Nooit",
  "user.settings.notifications.onlyMentions": "Enkele voor vermeldingen en privé berichten",
  "user.settings.push_notification.away": "Afwezig of offline",
  "user.settings.push_notification.disabled": "Push-berichten zijn niet ingeschakeld",
  "user.settings.push_notification.disabled_long": "Push-meldingen zijn niet ingeschakeld door de Systeembeheerder.",
  "user.settings.push_notification.offline": "Offline",
  "user.settings.push_notification.online": "Online, afwezig of offline",
  "web.root.signup_info": "Alle team communicatie op een plaats, doorzoekbaar en van overal bereikbaar"
}
