[
  {
    "id": "api.admin.add_certificate.open.app_error",
    "translation": "Nie można otworzyć pliku certyfikatu."
  },
  {
    "id": "api.admin.add_certificate.no_file.app_error",
    "translation": "Brak pliku pod \"certyfikat\" w żądaniu."
  },
  {
    "id": "api.admin.add_certificate.array.app_error",
    "translation": "Brak pliku pod \"certyfikat\" w żądaniu."
  },
  {
    "id": "September",
    "translation": "Wrzesień"
  },
  {
    "id": "October",
    "translation": "Październik"
  },
  {
    "id": "November",
    "translation": "Listopad"
  },
  {
    "id": "May",
    "translation": "Maj"
  },
  {
    "id": "March",
    "translation": "Marzec"
  },
  {
    "id": "June",
    "translation": "Czerwiec"
  },
  {
    "id": "July",
    "translation": "Lipiec"
  },
  {
    "id": "January",
    "translation": "Styczeń"
  },
  {
    "id": "February",
    "translation": "Luty"
  },
  {
    "id": "December",
    "translation": "Grudzień"
  },
  {
    "id": "August",
    "translation": "Sierpień"
  },
  {
    "id": "April",
    "translation": "Kwiecień"
  },
  {
    "id": "api.admin.saml.failure_get_metadata_from_idp.app_error",
    "translation": "Nie udało się uzyskać metadanych z URL Identity Provider."
  },
  {
    "id": "api.admin.remove_certificate.delete.app_error",
    "translation": "Podczas usuwania certyfikatu wystąpił błąd."
  },
  {
    "id": "api.admin.ldap.not_available.app_error",
    "translation": "LDAP jest niedostępne."
  },
  {
    "id": "api.admin.get_brand_image.storage.app_error",
    "translation": "Przechowywanie obrazów nie zostało skonfigurowane."
  },
  {
    "id": "api.admin.file_read_error",
    "translation": "Błąd podczas odczytywania pliku dziennika."
  },
  {
    "id": "api.admin.delete_brand_image.storage.not_found",
    "translation": "Nie można usunąć obrazu marki, nie znaleziono."
  },
  {
    "id": "api.admin.add_certificate.saving.app_error",
    "translation": "Nie można zapisać pliku certyfikatu."
  },
  {
    "id": "api.admin.add_certificate.parseform.app_error",
    "translation": "Błąd przetwarzania żądania wielopostaciowego"
  },
  {
    "id": "api.admin.saml.failure_parse_idp_certificate.app_error",
    "translation": "Napotkany błąd podczas przetwarzania informacji metadanych otrzymanych od Identity Provider do certyfikatu."
  },
  {
    "id": "Boards",
    "translation": "Tablice"
  }
]
